instant_article/__init__.py
instant_article/config/__init__.py
instant_article/config/instant_article.py
instant_article/controllers/__init__.py
instant_article/controllers/instant_article_controller.py
instant_article/interfaces/__init__.py
instant_article/interfaces/instant_article_interface.py
instant_article/models/__init__.py
instant_article/models/instant_article.py
instant_article/models/instant_article_resolver.py
instant_article/providers/__init__.py
instant_article/providers/instant_article_provider.py
instant_article/routes/__init__.py
instant_article/routes/route.py
instant_article/templates/__init__.py
instant_article/templates/feeds.html
instant_article/templates/instant-article.html
masonite_instant_article-0.1.2.dist-info/LICENSE
masonite_instant_article-0.1.2.dist-info/METADATA
masonite_instant_article-0.1.2.dist-info/WHEEL
masonite_instant_article-0.1.2.dist-info/top_level.txt
masonite_instant_article-0.1.2.dist-info/RECORD
