Metadata-Version: 2.1
Name: masonite-instant-article
Version: 0.1.2
Summary: Instant Article for Masonite
Home-page: https://github.com/py-package/masonite-instant-articles
Author: Yubaraj Shrestha
Author-email: yubaraj@pypackage.com
License: MIT
Keywords: masonite,instant articles,development,package
Classifier: Framework :: Masonite
Classifier: License :: OSI Approved :: MIT License
Classifier: Operating System :: OS Independent
Classifier: Programming Language :: Python :: 3.8
Classifier: Programming Language :: Python :: 3.9
Classifier: Programming Language :: Python :: 3.10
Classifier: Topic :: Software Development :: Libraries :: Python Modules
License-File: LICENSE
Requires-Dist: masonite (>=4.0<5.0)
Provides-Extra: dev
Requires-Dist: black ; extra == 'dev'
Requires-Dist: flake8 ; extra == 'dev'
Requires-Dist: coverage ; extra == 'dev'
Requires-Dist: pytest ; extra == 'dev'
Requires-Dist: pytest-cov ; extra == 'dev'
Requires-Dist: twine (>=1.5.0) ; extra == 'dev'
Requires-Dist: wheel ; extra == 'dev'
